threado/__init__.py
threado/simple_thread_runner.py
threado/temp.py
threado/test_simple_thread_runner.py
threado-1.6.dist-info/LICENSE
threado-1.6.dist-info/METADATA
threado-1.6.dist-info/WHEEL
threado-1.6.dist-info/top_level.txt
threado-1.6.dist-info/RECORD
