Metadata-Version: 2.1
Name: threado
Version: 1.6
Summary: threado
Home-page: https://github.com/AlexNg9527/threado
Author: Alex Ng
Author-email: alex_q_wu@qq.com
Maintainer: Alex Ng
Maintainer-email: alex_q_wu@qq.com
License: MIT
Platform: UNKNOWN
Classifier: Programming Language :: Python :: 3
License-File: LICENSE
Requires-Dist: loguru
